{
  "id": "168d47e7-5183-4c61-a9d1-ad03ddeb51f3",
  "url": "https://www.rollingstone.com/music/music-news/the-guess-who-united-states-reunion-tour-dates-1235523613/",
  "normalizedUrl": "https://rollingstone.com/music/music-news/the-guess-who-united-states-reunion-tour-dates-1235523613",
  "title": "The Guess Who Announce Extensive United States Reunion Tour",
  "source": "Rolling Stone",
  "feedUrl": "https://www.rollingstone.com/feed/",
  "publishedAt": "Tue, 03 Mar 2026 15:00:00 +0000",
  "fetchedAt": "2026-03-03T19:20:36.603Z",
  "author": "Andy Greene",
  "contentHash": "a6d789ef8b220a0b",
  "fullText": "“Randy and I are incredibly grateful that our music has endured all these years,” says guitarist Randy Bachman. “Knowing that people still want to hear these songs live means everything to us”\n \n The Guess Who — featuring core members Burton Cummings and Randy Bachman — are hitting the road this summer for their first U.S. tour in 24 years. The run kicks off June 25 in Shakopee, Minnesota, and wraps up Aug. 22 in Seattle. (It’s bookended by shows in their native Canada.) Former Eagles guitarist Don Felder will serve as the opening act.\n\n “Randy and I are incredibly grateful that our music has endured all these years,” Bachman said in a statement. “Knowing that people still want to hear these songs live means everything to us, and when we go out on stage, our goal is to truly honour the music.”\n\n Cummings added: “I’m really excited about reuniting with Burton and touring again as the Guess Who. We created an amazing body of work together, along with memories that have lasted for decades, and those songs are still as strong as ever. I can’t wait to sing them with everyone very soon.”\n\n Up until this year, Cummings and Bachman hadn’t performed as the Guess Who since SARSfest in 2003. In the years that followed, former Guess Who bassist Jim Kale put together a new lineup that sparked a bitter legal fight that wasn’t resolved until 2024 when Cummings and Bachman reclaimed the name rights. \n\n \n\n “The fake band was using music that we wrote, and Burton sang on, to promote their shows,” Cummings recently told Rolling Stone. “And some of these guys weren’t even born when those things were hits. These clowns, they were actually taking our real albums to meet and greets and signing our pictures. I was in Philadelphia one time and I opened a Live at the Paramount album. I was going to sign it for this kid. And I opened the album and someone else had already signed my picture.”\n\n The new lineup of the Guess Who — which also includes drummer Sean Fitzsimons, bassist Jeff Jones, percussionist Nick Sinopoli, and guitarists Tim Bovaconti and Joe Augello — played their first show Jan. 31 in Niagara Falls, Ontario. The set is heavy on classics like “American Woman,” “These Eyes,” “Undun,” and “No Time” in addition to the Bachman-Turner Overdrive classics “Let It Ride,” “You Ain’t Seen Nothing Yet,” and “Takin’ Care of Business.”\n\n \n\n \n\n \n\n \n Editor’s picks\n \n \n\n \n \n\n There hasn’t been a new Guess Who album since 1975’s Power in the Music, and the last one to feature Bachman was 1970’s American Woman. That remains unlikely to change in the near future since the focus is on touring, but they aren’t ruling it out. “Randy and I will be together for hours and hours on the tour bus,” Cummings recently told Rolling Stone. “Sometimes he picks up a guitar, starts playing riffs, and I start singing over them. So we could capture some of that wonder of the old days. You never know. I never say never.”\n\n \n\n \n\n \n Trending Stories\n \n \n\n \n \n\n The Guess Who’s Taking It Back Tour Dates:\n\n May 26 – Moncton, NB @ Avenir CentreMay 27 – Halifax, NS @ Scotiabank CentreMay 29 – Laval, QC @ Place BellMay 30 – Toronto, ON @ Scotiabank ArenaJune 1 – Hamilton, ON @ TD ColiseumJune 2 – London, ON @ Canada Life PlaceJune 5 – Winnipeg, MB @ Canada Life CentreJune 6 – Saskatoon, SK @ SaskTel CentreJune 8 – Calgary, AB @ Scotiabank SaddledomeJune 10 – Edmonton, AB @ Rogers PlaceJune 25 – Shakopee, MN @ Mystic Lake AmphitheaterJune 27 – Cincinnati, OH @ Riverbend Music CenterJune 28 – Cuyahoga, OH @ Blossom Music CenterJune 30 – Chicago, IL @ Huntington Bank Pavilion at Northerly IslandJuly 1 – Grand Rapids, MI @ Acrisure AmphitheaterJuly 3 – Clarkston, MI @ Pine Knob Music TheatreJuly 5 – Holmdel, NJ @ PNC Bank Arts CenterJuly 7 – Syracuse, NY @ Empower Federal Credit Union Amphitheater at LakeviewJuly 8 – Gilford, NH @ BankNH PavilionJuly 10 – Wantagh, NY @ Northwell at Jones Beach TheaterJuly 11 – Atlantic City, NJ @ Hard Rock Hotel & Casino Atlantic CityJuly 14 – Saratoga Springs, NY @ Albany Med Health System at SPACJuly 16 – Uncasville, CT @ Mohegan Sun ArenaJuly 17 – Boston, MA @ Leader Bank PavilionJuly 19 – Ottawa, ON @ Ottawa BluesfestAugust 6 – Atlanta, GA @ Synovus Bank Amphitheater at Chastain ParkAugust 8 – Houston, TX @ Smart Financial Centre at Sugar LandAugust 9 – Fort Worth, TX @ Dickies ArenaAugust 12 – Denver, CO @ Fiddlers Green AmphitheaterAugust 14 – Salt Lake City, UT @ Maverik CenterAugust 15 – Las Vegas, NV @ Fontainebleau Las VegasAugust 17 – Phoenix, AZ @ Arizona Financial TheatreAugust 19 – Los Angeles, CA @ Greek TheatreAugust 22 – Seattle, WA @ Climate Pledge ArenaAugust 23 – Vancouver, BC @ The Pacific National Exhibition",
  "summary": "“Randy and I are incredibly grateful that our music has endured all these years,” says guitarist Randy Bachman. “Knowing that people still want to hear these songs live means everything to us”",
  "categories": [
    "entertainment"
  ]
}