{
  "id": "98f1df9f-8887-4e3c-85af-2a894492e21a",
  "url": "https://thehill.com/homenews/state-watch/5762931-live-results-arkansas-gubernatorial-primary/",
  "normalizedUrl": "https://thehill.com/homenews/state-watch/5762931-live-results-arkansas-gubernatorial-primary",
  "title": "Live results: Arkansas governor’s Democratic primary underway",
  "source": "The Hill",
  "feedUrl": "https://thehill.com/feed/",
  "publishedAt": "Tue, 03 Mar 2026 22:00:00 +0000",
  "fetchedAt": "2026-03-03T22:53:21.553Z",
  "author": "The Hill Staff",
  "contentHash": "a9d34174a2e06e97",
  "fullText": "With Arkansas Gov. Sarah Huckabee Sanders (R) advancing to the November general election, just Democrats will host a gubernatorial primary on Tuesday. Democratic candidates include state Sen. Fredrick Love,and Supha Xayprasith-Mays, a business leaders. The GOP is expected to hang on to the governor’s office in November. Follow Decision Desk HQ’s live results here.",
  "summary": "With Arkansas Gov. Sarah Huckabee Sanders (R) advancing to the November general election, just Democrats will host a gubernatorial primary on Tuesday. Democratic candidates include state Sen. Fredrick Love,and Supha Xayprasith-Mays, a business leaders. The GOP is expected to hang on to the governor’s office in November. Follow Decision Desk HQ’s live results here.",
  "imageUrl": "https://thehill.com/wp-content/uploads/sites/2/2026/03/AP24085607892858-e1772470429607.jpg?w=900",
  "categories": [
    "digital"
  ]
}