{
  "id": "9a595a4b-4a5b-445d-8744-8b2c79168c00",
  "url": "https://techcrunch.com/2026/03/03/audible-launches-a-cheaper-standard-subscription-plan-challenging-spotify/",
  "normalizedUrl": "https://techcrunch.com/2026/03/03/audible-launches-a-cheaper-standard-subscription-plan-challenging-spotify",
  "title": "Audible launches a cheaper ‘Standard’ subscription plan, challenging Spotify",
  "source": "TechCrunch",
  "feedUrl": "https://techcrunch.com/feed/",
  "publishedAt": "Tue, 03 Mar 2026 16:40:19 +0000",
  "fetchedAt": "2026-03-03T22:53:48.240Z",
  "author": "Aisha Malik",
  "contentHash": "05b3307c1f798634",
  "fullText": "Audible is rolling out a cheaper “Standard” subscription plan that costs $8.99 per month, the Amazon-owned company announced on Tuesday. The new plan is $6 cheaper than the platform’s existing “Premium” plan, which costs $14.95 per month. \n\nThe Standard plan includes one audiobook per month from Audible’s catalog and unlimited listening from a curated library that includes a selection of Audible Originals. \n\nUnder the new Standard plan, subscribers will lose access to the audiobooks they’ve consumed when they unsubscribe. The Premium plan lets users keep the audiobooks they’ve listened to even if they unsubscribe.\n\nThe Standard plan also includes access to nearly 200 of the most popular titles available on the Wondery+ app, which is shutting down in the coming months.\n\nThe Standard plan is launching in the United States, the United Kingdom, Canada, Australia, Germany, and France. Audible is testing the plan in additional markets, the company says.\n\nThe launch of the new subscription plans comes as Audible is facing growing competition from Spotify, which launched audiobooks in 2022 and has bundled the format with music and podcasts as part of its own Premium subscription.\n\nSpotify said last October that the number of users listening to audiobooks rose 36% over the past year, and listening hours increased 37%. Additionally, it noted that more than half of Spotify’s 281 million premium subscribers have engaged with an audiobook.\n\n \n Techcrunch event\n \n \n San Francisco, CA\n |\n October 13-15, 2026\n \n \n \n \n\nSpotify recently hiked the price of its monthly subscription plan for the third time in three years, potentially opening the door to competitors like Audible.\n\n“By expanding our membership options, we’re maximizing access for lighter listeners while enabling publishers and creators to reach new audiences — a win-win that grows the entire audiobook category,” said Cynthia Chu, chief financial and growth officer at Audible, in a press release.\n\nAudible says early testing of the new plan showed strong member acquisition and retention rates, as testing in the United Kingdom and Australia showed that the plan drove a double-digit increase in new member sign-ups compared with previous offerings. With its expansion to new markets, the Standard plan is projected to bring in millions of new customers, the company says. \n\n \n \n \n \n\n \n\n Aisha is a consumer news reporter at TechCrunch. Prior to joining the publication in 2021, she was a telecom reporter at MobileSyrup. Aisha holds an honours bachelor’s degree from University of Toronto and a master’s degree in journalism from Western University.\n\nYou can contact or verify outreach from Aisha by emailing aisha@techcrunch.com or via encrypted message at aisha_malik.01 on Signal. \n\n \n \n View Bio",
  "summary": "Under the new Standard plan, subscribers will lose access to the audiobooks they've consumed when they unsubscribe. The Premium plan lets users keep the audiobooks they’ve listened to even if they unsubscribe.",
  "categories": [
    "tech"
  ]
}