{
  "id": "d9481acf-c4e8-4f57-9b29-5d3d8b93a8d1",
  "url": "https://www.nytimes.com/2026/03/02/world/canada/carney-india-modi.html",
  "normalizedUrl": "https://nytimes.com/2026/03/02/world/canada/carney-india-modi.html",
  "title": "Carney Hails New Ties Between Canada and India, Setting Aside Rift Over Killing",
  "source": "NYT World",
  "feedUrl": "https://rss.nytimes.com/services/xml/rss/nyt/World.xml",
  "publishedAt": "Mon, 02 Mar 2026 17:27:42 +0000",
  "fetchedAt": "2026-03-03T22:52:03.669Z",
  "author": "Ian Austen",
  "contentHash": "f1908b741e7db710",
  "fullText": "Prime Minister Mark Carney focused on business during a meeting with his Indian counterpart, Narendra Modi, with little mention of India’s alleged role in a deadly shooting in 2023.",
  "summary": "Prime Minister Mark Carney focused on business during a meeting with his Indian counterpart, Narendra Modi, with little mention of India’s alleged role in a deadly shooting in 2023.",
  "categories": [
    "broadsheet"
  ]
}