[
  {
    "id": "b52f8b84-19ce-44db-89dc-b31e82b6fba8",
    "clusterId": "ff1f1333-3a58-4786-96d0-473686b82d21",
    "text": "Apple unveiled M5 Pro and M5 Max chips on Tuesday, March 3, 2026",
    "status": "undisputed",
    "supportingSources": [
      "TechCrunch",
      "Engadget",
      "Ars Technica",
      "CNBC"
    ],
    "disputingSources": [],
    "firstSeenAt": "2026-03-03T23:18:55.896Z",
    "lastUpdatedAt": "2026-03-03T23:18:55.896Z"
  },
  {
    "id": "cf442d52-3475-42da-a00e-a1c833f44bd4",
    "clusterId": "ff1f1333-3a58-4786-96d0-473686b82d21",
    "text": "Both M5 Pro and M5 Max feature an 18-core CPU",
    "status": "undisputed",
    "supportingSources": [
      "TechCrunch",
      "Engadget",
      "Ars Technica"
    ],
    "disputingSources": [],
    "firstSeenAt": "2026-03-03T20:05:49.176Z",
    "lastUpdatedAt": "2026-03-03T23:18:55.896Z"
  },
  {
    "id": "f366c91c-e745-4912-9873-81d1a3c5312a",
    "clusterId": "ff1f1333-3a58-4786-96d0-473686b82d21",
    "text": "The chips use new 'Fusion Architecture' that merges two dies into a single SoC",
    "status": "undisputed",
    "supportingSources": [
      "TechCrunch",
      "Engadget",
      "Ars Technica"
    ],
    "disputingSources": [],
    "firstSeenAt": "2026-03-03T23:18:55.896Z",
    "lastUpdatedAt": "2026-03-03T23:18:55.896Z"
  },
  {
    "id": "d5e5297b-4ff3-422a-a680-5e829e6bc04f",
    "clusterId": "ff1f1333-3a58-4786-96d0-473686b82d21",
    "text": "The CPU features six 'super cores' and 12 performance cores",
    "status": "undisputed",
    "supportingSources": [
      "TechCrunch",
      "Engadget",
      "Ars Technica"
    ],
    "disputingSources": [],
    "firstSeenAt": "2026-03-03T23:18:55.896Z",
    "lastUpdatedAt": "2026-03-03T23:18:55.896Z"
  },
  {
    "id": "cd5a5b90-2859-4453-ae7a-5d9bce3e9434",
    "clusterId": "ff1f1333-3a58-4786-96d0-473686b82d21",
    "text": "CPU performance is up to 30% faster for pro workloads compared to M4 generation",
    "status": "undisputed",
    "supportingSources": [
      "TechCrunch",
      "Engadget"
    ],
    "disputingSources": [],
    "firstSeenAt": "2026-03-03T23:18:55.896Z",
    "lastUpdatedAt": "2026-03-03T23:18:55.896Z"
  },
  {
    "id": "29a1c562-a56b-4a82-87d3-4d1c16d946e7",
    "clusterId": "ff1f1333-3a58-4786-96d0-473686b82d21",
    "text": "M5 Pro and M5 Max offer over 4x the peak GPU compute for AI compared to previous generation",
    "status": "undisputed",
    "supportingSources": [
      "TechCrunch",
      "Engadget"
    ],
    "disputingSources": [],
    "firstSeenAt": "2026-03-03T20:05:49.176Z",
    "lastUpdatedAt": "2026-03-03T23:18:55.896Z"
  },
  {
    "id": "ad7a0499-7e00-440e-8afc-2d61a7cdce91",
    "clusterId": "ff1f1333-3a58-4786-96d0-473686b82d21",
    "text": "Graphics performance is up to 20% faster overall",
    "status": "undisputed",
    "supportingSources": [
      "TechCrunch",
      "Ars Technica"
    ],
    "disputingSources": [],
    "firstSeenAt": "2026-03-03T20:05:49.176Z",
    "lastUpdatedAt": "2026-03-03T23:18:55.896Z"
  },
  {
    "id": "343f9491-b1f0-417e-b1e1-f406d83fbecf",
    "clusterId": "ff1f1333-3a58-4786-96d0-473686b82d21",
    "text": "Ray-tracing workloads improve by up to 35%",
    "status": "undisputed",
    "supportingSources": [
      "TechCrunch",
      "Engadget"
    ],
    "disputingSources": [],
    "firstSeenAt": "2026-03-03T20:05:49.176Z",
    "lastUpdatedAt": "2026-03-03T23:18:55.896Z"
  },
  {
    "id": "bda20c8f-d947-4206-ab0b-aa2e76c2d8a1",
    "clusterId": "ff1f1333-3a58-4786-96d0-473686b82d21",
    "text": "M5 Pro supports up to 64GB of unified memory with 307GB/s bandwidth",
    "status": "undisputed",
    "supportingSources": [
      "TechCrunch",
      "Ars Technica"
    ],
    "disputingSources": [],
    "firstSeenAt": "2026-03-03T20:05:49.176Z",
    "lastUpdatedAt": "2026-03-03T23:18:55.896Z"
  },
  {
    "id": "aabb55c5-0535-48cd-b9f6-73c6acbc6b41",
    "clusterId": "ff1f1333-3a58-4786-96d0-473686b82d21",
    "text": "M5 Max supports up to 128GB of unified memory with 614GB/s bandwidth",
    "status": "undisputed",
    "supportingSources": [
      "TechCrunch",
      "Ars Technica"
    ],
    "disputingSources": [],
    "firstSeenAt": "2026-03-03T20:05:49.176Z",
    "lastUpdatedAt": "2026-03-03T23:18:55.896Z"
  },
  {
    "id": "af451427-6c04-40f3-8ac4-5c4543d87b85",
    "clusterId": "ff1f1333-3a58-4786-96d0-473686b82d21",
    "text": "M5 Pro GPU has up to 20 cores",
    "status": "undisputed",
    "supportingSources": [
      "Engadget",
      "Ars Technica"
    ],
    "disputingSources": [],
    "firstSeenAt": "2026-03-03T23:18:55.896Z",
    "lastUpdatedAt": "2026-03-03T23:18:55.896Z"
  },
  {
    "id": "89165309-8d71-458c-92ae-861e6b7270f1",
    "clusterId": "ff1f1333-3a58-4786-96d0-473686b82d21",
    "text": "M5 Max GPU has up to 40 cores",
    "status": "undisputed",
    "supportingSources": [
      "TechCrunch",
      "Engadget",
      "Ars Technica"
    ],
    "disputingSources": [],
    "firstSeenAt": "2026-03-03T23:18:55.896Z",
    "lastUpdatedAt": "2026-03-03T23:18:55.896Z"
  },
  {
    "id": "d9ebdea3-d6a8-45ac-9f60-838d50b6a9fa",
    "clusterId": "ff1f1333-3a58-4786-96d0-473686b82d21",
    "text": "New MacBook Pro models are available for preorder March 4 with availability March 11",
    "status": "undisputed",
    "supportingSources": [
      "TechCrunch",
      "Engadget"
    ],
    "disputingSources": [],
    "firstSeenAt": "2026-03-03T20:05:49.176Z",
    "lastUpdatedAt": "2026-03-03T23:18:55.896Z"
  },
  {
    "id": "5454b1e4-df4e-41c6-bd40-57e73ab89970",
    "clusterId": "ff1f1333-3a58-4786-96d0-473686b82d21",
    "text": "14-inch MacBook Pro with M5 Pro starts at $2,199, up from $1,999",
    "status": "undisputed",
    "supportingSources": [
      "Ars Technica",
      "Engadget",
      "TechCrunch"
    ],
    "disputingSources": [],
    "firstSeenAt": "2026-03-03T23:18:55.896Z",
    "lastUpdatedAt": "2026-03-03T23:18:55.896Z"
  },
  {
    "id": "46e8bf8b-daa4-4d81-b155-25bdd45b8e40",
    "clusterId": "ff1f1333-3a58-4786-96d0-473686b82d21",
    "text": "16-inch MacBook Pro with M5 Pro starts at $2,699, up from $2,499",
    "status": "undisputed",
    "supportingSources": [
      "Ars Technica",
      "Engadget",
      "TechCrunch"
    ],
    "disputingSources": [],
    "firstSeenAt": "2026-03-03T23:18:55.896Z",
    "lastUpdatedAt": "2026-03-03T23:18:55.896Z"
  },
  {
    "id": "ce27b631-6209-4011-9e94-1db5dc18d166",
    "clusterId": "ff1f1333-3a58-4786-96d0-473686b82d21",
    "text": "M5 Pro models now come with 1TB base storage, M5 Max models with 2TB base storage",
    "status": "undisputed",
    "supportingSources": [
      "Ars Technica",
      "Engadget",
      "CNBC"
    ],
    "disputingSources": [],
    "firstSeenAt": "2026-03-03T23:18:55.896Z",
    "lastUpdatedAt": "2026-03-03T23:18:55.896Z"
  },
  {
    "id": "0c41d3eb-ea76-49ae-a069-989d87bdfbff",
    "clusterId": "ff1f1333-3a58-4786-96d0-473686b82d21",
    "text": "MacBook Air M5 starts at $1,099 for 13-inch model, up from $999",
    "status": "undisputed",
    "supportingSources": [
      "Engadget",
      "CNBC",
      "TechCrunch"
    ],
    "disputingSources": [],
    "firstSeenAt": "2026-03-03T23:18:55.896Z",
    "lastUpdatedAt": "2026-03-03T23:18:55.896Z"
  },
  {
    "id": "fc01b2d7-a5df-4ddb-ac74-c3c57c6e4986",
    "clusterId": "ff1f1333-3a58-4786-96d0-473686b82d21",
    "text": "MacBook Air M5 starts at $1,299 for 15-inch model, up from $1,199",
    "status": "undisputed",
    "supportingSources": [
      "Engadget",
      "CNBC"
    ],
    "disputingSources": [],
    "firstSeenAt": "2026-03-03T23:18:55.896Z",
    "lastUpdatedAt": "2026-03-03T23:18:55.896Z"
  },
  {
    "id": "2baf4826-3e3c-4b5e-9232-e09d7e3b2537",
    "clusterId": "ff1f1333-3a58-4786-96d0-473686b82d21",
    "text": "MacBook Air M5 doubles base storage from 256GB to 512GB",
    "status": "undisputed",
    "supportingSources": [
      "Engadget",
      "CNBC"
    ],
    "disputingSources": [],
    "firstSeenAt": "2026-03-03T23:18:55.896Z",
    "lastUpdatedAt": "2026-03-03T23:18:55.896Z"
  },
  {
    "id": "1803509e-4460-43c7-9ce7-a57df7352e02",
    "clusterId": "ff1f1333-3a58-4786-96d0-473686b82d21",
    "text": "Apple N1 wireless chip provides Wi-Fi 7 and Bluetooth 6 connectivity",
    "status": "undisputed",
    "supportingSources": [
      "Ars Technica",
      "Engadget"
    ],
    "disputingSources": [],
    "firstSeenAt": "2026-03-03T20:05:49.176Z",
    "lastUpdatedAt": "2026-03-03T23:18:55.896Z"
  },
  {
    "id": "1a9486ab-8e4b-4d4b-a444-7412bce305e8",
    "clusterId": "ff1f1333-3a58-4786-96d0-473686b82d21",
    "text": "Price increases are attributed to RAM shortage affecting memory supply",
    "status": "undisputed",
    "supportingSources": [
      "TechCrunch",
      "CNBC"
    ],
    "disputingSources": [],
    "firstSeenAt": "2026-03-03T23:18:55.896Z",
    "lastUpdatedAt": "2026-03-03T23:18:55.896Z"
  },
  {
    "id": "f25151c3-604b-4816-8f0f-741fd5633c9a",
    "clusterId": "ff1f1333-3a58-4786-96d0-473686b82d21",
    "text": "Apple claims the 'super cores' are the world's fastest CPU cores",
    "status": "undisputed",
    "supportingSources": [
      "Engadget"
    ],
    "disputingSources": [],
    "firstSeenAt": "2026-03-03T23:18:55.896Z",
    "lastUpdatedAt": "2026-03-03T23:18:55.896Z"
  },
  {
    "id": "e6475e9b-f987-47f1-9dd1-c3bac52d2e90",
    "clusterId": "ff1f1333-3a58-4786-96d0-473686b82d21",
    "text": "Storage in new MacBook Pro is up to 2x faster than previous generation",
    "status": "undisputed",
    "supportingSources": [
      "Ars Technica",
      "Engadget"
    ],
    "disputingSources": [],
    "firstSeenAt": "2026-03-03T23:18:55.896Z",
    "lastUpdatedAt": "2026-03-03T23:18:55.896Z"
  }
]