{
  "id": "745ba9e4-aa90-4ac0-8508-6d5afae6a63e",
  "url": "https://techcrunch.com/2026/02/25/snapchat-announces-the-snappys-its-first-ever-creator-awards-show/",
  "normalizedUrl": "https://techcrunch.com/2026/02/25/snapchat-announces-the-snappys-its-first-ever-creator-awards-show",
  "title": "Snapchat announces ‘The Snappys,’ its first-ever creator awards show",
  "source": "TechCrunch",
  "feedUrl": "https://techcrunch.com/feed/",
  "publishedAt": "Wed, 25 Feb 2026 19:54:18 +0000",
  "fetchedAt": "2026-02-26T01:24:10.476Z",
  "author": "Aisha Malik",
  "contentHash": "7ef359c6bba0a7d4",
  "fullText": "Snapchat announced on Wednesday that it’s hosting its first-ever awards show on March 21. The social media giant says the awards show, called “The Snappys,” is designed to celebrate “the creators shaping culture on Snapchat.”\n\nCreators will receive awards like “Spotlight MVP,” “Best Storyteller,” and “Breakout Creator of the Year,” alongside awards across fashion, beauty, sports, music, food, and games. Additional categories include collaboration, comedy, and cultural impact.\n\n“Together, these honors reflect the many ways creators spark conversations, build community, and define culture on Snapchat,” the company wrote in a blog post. “The Snappys reinforces Snapchat’s ongoing commitment to celebrating creators not just as users, but as artists, entertainers, and cultural leaders.”\n\nSnapchat is the latest social media platform to launch awards for creators. Meta-owned Instagram introduced a new “Ring” award last October to recognize creators around the world. Instagram announced the 25 winners online, and each winner received a physical custom ring designed by English fashion designer Grace Wales Bonner, along with a digital golden ring around their Instagram profile.\n\nIn November, TikTok launched its first-ever TikTok Awards show in the U.S. Like Snapchat, Instagram handed out category-specific awards, like “Creator of the Year,” “Video of the Year,” “Muse of the Year,” “Breakthrough Artist of the Year,” and more. It’s worth noting that TikTok has also hosted awards shows in other countries, including Germany, Mexico, and Korea.\n\nSnapchat’s awards are more in line with TikTok’s, as it will also host a traditional awards show where the winners will be revealed live at the event. The company says the show will bring together “creators, industry leaders, and special guests.” One of the “special guests” is DJ Khaled, who will be receiving Snapchat’s “Lifetime Achievement Award.”\n\nBy launching awards, Snapchat and its rivals are positioning themselves as more than just social media apps and as notable players in the entertainment industry. \n\n \n Techcrunch event\n \n \n Boston, MA\n |\n June 9, 2026\n \n \n \n \n\nThe Snappys will be hosted by comedian and creator Matt Friend and will take place at Snap‘s Santa Monica headquarters. Snapchat says it will release more details, including lists of nominees, in the coming weeks. \n\n \n \n \n \n\n \n\n Aisha is a consumer news reporter at TechCrunch. Prior to joining the publication in 2021, she was a telecom reporter at MobileSyrup. Aisha holds an honours bachelor’s degree from University of Toronto and a master’s degree in journalism from Western University.\n\nYou can contact or verify outreach from Aisha by emailing aisha@techcrunch.com or via encrypted message at aisha_malik.01 on Signal. \n\n \n \n View Bio",
  "summary": "Snapchat is the latest social media platform to launch awards for creators, joining TikTok and Instagram.",
  "categories": [
    "tech"
  ]
}