{
  "id": "d3b1e9d1-08fd-4eb4-b763-3fb680523271",
  "url": "https://abcnews.com/International/video/uber-previews-air-taxi-service-130508410",
  "normalizedUrl": "https://abcnews.com/International/video/uber-previews-air-taxi-service-130508410",
  "title": "WATCH:  Uber previews its 'air taxi' service",
  "source": "ABC News",
  "feedUrl": "https://abcnews.go.com/abcnews/topstories",
  "publishedAt": "Wed, 25 Feb 2026 20:17:13 -0500",
  "fetchedAt": "2026-02-26T01:23:53.522Z",
  "contentHash": "02e6903aa1a43ce1",
  "fullText": "Uber previews its 'air taxi' serviceABC News' Sam Sweeney breaks down Uber's program \"air taxi\" which is expected to hit the market in Dubai later this year.February 25, 2026",
  "summary": "ABC News' Sam Sweeney breaks down Uber's program \"air taxi\" which is expected to hit the market in Dubai later this year.",
  "categories": [
    "cable"
  ]
}