{
  "id": "e59ea792-0f66-497c-9408-c3737ca3afa0",
  "url": "https://arstechnica.com/gaming/2026/02/new-york-sues-valve-for-enabling-illegal-gambling-with-loot-boxes/",
  "normalizedUrl": "https://arstechnica.com/gaming/2026/02/new-york-sues-valve-for-enabling-illegal-gambling-with-loot-boxes",
  "title": "New York sues Valve for enabling \"illegal gambling\" with loot boxes",
  "source": "Ars Technica",
  "feedUrl": "https://feeds.arstechnica.com/arstechnica/index",
  "publishedAt": "Thu, 26 Feb 2026 14:57:36 +0000",
  "fetchedAt": "2026-02-26T17:24:15.495Z",
  "author": "\n                    Kyle Orland\n                ",
  "contentHash": "7799d9d85016c9c3",
  "fullText": "Opening a valuable skin like this in a loot box is akin to winning a lottery, New York alleges in a new lawsuit.\n \n \n \n \n \n \n \n Opening a valuable skin like this in a loot box is akin to winning a lottery, New York alleges in a new lawsuit.\n\n \n Credit:\n\n \n \n Twitter / Luksusbums\n\n \n \n \n \n \n \n\nThe lawsuit also takes Valve to task for allowing third-party sites that facilitate the resale of in-game skins for cash. While the suit notes that Valve has “sporadically enforced” rules against so-called skin gambling sites—which use Steam inventories as virtual chips for gambling games—it alleges that Valve “has not acted against sites that permit the sale of Valve’s virtual items.” The suit cites “internal communications” from numerous Valve employees suggesting that the company was OK with such “cash-out services” for Steam items as long as off-platform gambling wasn’t explicitly involved.\nWe’ll see you in court\nIn a press release announcing the suit, state Attorney General Letitia James said the gambling Valve’s system enables can “lead to serious addiction problems, especially for our young people. … These features are addictive, harmful, and illegal, and my office is suing to stop Valve’s illegal conduct and protect New Yorkers.”\nBack in 2016, Valve faced a pair of civil lawsuits from parents concerned about Valve’s connection to skin gambling sites—those suits were eventually dismissed. Around the same time, Valve received a letter from Washington state threatening “civil or criminal action” if Valve didn’t crack down on skin gambling, but the state stopped short of filing a lawsuit in that matter.\nIn addition to asking Valve to modify or eliminate its loot box system, the New York suit asks for Valve to make “full restitution to consumers” for the disgorgement of “all monies” received from its gambling system, and for fines of “three times the amount of its gain.” Ars Technica has reached out to Valve for comment.",
  "summary": "The ability to resell Steam items for real value is key to the state's case.",
  "categories": [
    "tech"
  ]
}